builders.py
train.py
deepbind-0.1.0.dist-info/METADATA
deepbind-0.1.0.dist-info/WHEEL
deepbind-0.1.0.dist-info/top_level.txt
deepbind-0.1.0.dist-info/RECORD
